{
  "hubs": [
    {
      "requirements": [],
      "warps": [
        {
          "x": 29,
          "y": 62,
          "ourMapGroup": 1,
          "ourMapNum": 0,
          "ourID": 0,
          "destID": 3,
          "destMapString": "MAP_ROUTE2_VIRIDIAN_FOREST_SOUTH_ENTRANCE",
          "gameName": "POKEMON FIRE",
          "destMapGroup": 15,
          "destMapNum": 0,
          "duplicates": [
            {
              "x": 28,
              "y": 62,
              "ourMapGroup": 1,
              "ourMapNum": 0,
              "ourID": 1,
              "destID": 3,
              "destMapString": "MAP_ROUTE2_VIRIDIAN_FOREST_SOUTH_ENTRANCE",
              "gameName": "POKEMON FIRE",
              "destMapGroup": 15,
              "destMapNum": 0,
              "duplicates": []
            },
            {
              "x": 30,
              "y": 62,
              "ourMapGroup": 1,
              "ourMapNum": 0,
              "ourID": 4,
              "destID": 3,
              "destMapString": "MAP_ROUTE2_VIRIDIAN_FOREST_SOUTH_ENTRANCE",
              "gameName": "POKEMON FIRE",
              "destMapGroup": 15,
              "destMapNum": 0,
              "duplicates": []
            }
          ]
        },
        {
          "x": 5,
          "y": 9,
          "ourMapGroup": 1,
          "ourMapNum": 0,
          "ourID": 2,
          "destID": 1,
          "destMapString": "MAP_ROUTE2_VIRIDIAN_FOREST_NORTH_ENTRANCE",
          "gameName": "POKEMON FIRE",
          "destMapGroup": 15,
          "destMapNum": 3,
          "duplicates": [
            {
              "x": 6,
              "y": 9,
              "ourMapGroup": 1,
              "ourMapNum": 0,
              "ourID": 3,
              "destID": 1,
              "destMapString": "MAP_ROUTE2_VIRIDIAN_FOREST_NORTH_ENTRANCE",
              "gameName": "POKEMON FIRE",
              "destMapGroup": 15,
              "destMapNum": 3,
              "duplicates": []
            },
            {
              "x": 4,
              "y": 9,
              "ourMapGroup": 1,
              "ourMapNum": 0,
              "ourID": 5,
              "destID": 1,
              "destMapString": "MAP_ROUTE2_VIRIDIAN_FOREST_NORTH_ENTRANCE",
              "gameName": "POKEMON FIRE",
              "destMapGroup": 15,
              "destMapNum": 3,
              "duplicates": []
            }
          ]
        }
      ]
    }
  ]
}